heathotspotsgee/__init__.py
heathotspotsgee/common.py
heathotspotsgee/heathotspotsgee.py
heathotspotsgee-0.0.1.dist-info/LICENSE
heathotspotsgee-0.0.1.dist-info/METADATA
heathotspotsgee-0.0.1.dist-info/WHEEL
heathotspotsgee-0.0.1.dist-info/top_level.txt
heathotspotsgee-0.0.1.dist-info/RECORD
