Metadata-Version: 2.1
Name: heathotspotsgee
Version: 0.0.1
Summary: Heat Hotspots using GEE
Home-page: https://github.com/Sub-esh/heathotspotsgee
Author: Subesh Bhattarai
Author-email: subsonicu571@gmail.com
License: MIT license
Keywords: heathotspotsgee
Classifier: Intended Audience :: Developers
Classifier: License :: OSI Approved :: MIT License
Classifier: Natural Language :: English
Classifier: Programming Language :: Python :: 3
Classifier: Programming Language :: Python :: 3.8
Classifier: Programming Language :: Python :: 3.9
Classifier: Programming Language :: Python :: 3.10
Classifier: Programming Language :: Python :: 3.11
Requires-Python: >=3.8
License-File: LICENSE
